genice2_cage/__init__.py
genice2_cage/formats/__init__.py
genice2_cage/formats/cage.py
genice2_cage-2.5.2.dist-info/METADATA
genice2_cage-2.5.2.dist-info/WHEEL
genice2_cage-2.5.2.dist-info/entry_points.txt
genice2_cage-2.5.2.dist-info/RECORD
