Metadata-Version: 2.1
Name: genice2-cage
Version: 2.5.2
Summary: A format plugin for GenIce2 to detect cages.
License: MIT
Author: vitroid
Author-email: vitroid@gmail.com
Requires-Python: >=3.10,<4.0
Classifier: License :: OSI Approved :: MIT License
Classifier: Programming Language :: Python :: 3
Classifier: Programming Language :: Python :: 3.10
Classifier: Programming Language :: Python :: 3.11
Classifier: Programming Language :: Python :: 3.12
Requires-Dist: GenIce2 (>=2.2.5.2,<3.0.0.0)
Requires-Dist: cycless (>=0.6.3)
Requires-Dist: graphstat (>=0.3.3,<0.4.0)
Requires-Dist: networkx (>=3.2.1)
Requires-Dist: numpy (>=1.26.4)
Requires-Dist: yaplotlib (>=0.1.2,<0.2.0)
